{
  "meta": {
    "key": "bbc",
    "label": "bbc",
    "source_url": "https://feeds.bbci.co.uk/news/rss.xml",
    "take": 2,
    "built_at": "2026-05-13T17:10:04.850Z"
  },
  "items": [
    {
      "title": "Trade, Iran and Taiwan on the agenda as Trump arrives in China for high-stakes talks with Xi",
      "url": "https://www.bbc.com/news/articles/c1w28qw1e0xo?at_medium=RSS&at_campaign=rss",
      "date": "2026-05-13T17:00:12.000Z"
    },
    {
      "title": "Why is there a row about an MSP's immigration status?",
      "url": "https://www.bbc.com/news/articles/c4g82j03w94o?at_medium=RSS&at_campaign=rss",
      "date": "2026-05-13T16:51:35.000Z"
    }
  ]
}
