{
  "meta": {
    "key": "bbc",
    "label": "bbc",
    "source_url": "https://feeds.bbci.co.uk/news/rss.xml",
    "take": 2,
    "built_at": "2026-03-13T12:39:35.298Z"
  },
  "items": [
    {
      "title": "Four crew members killed after US refuelling plane crashes in Iraq",
      "url": "https://www.bbc.com/news/articles/cy0dz5ql17vo?at_medium=RSS&at_campaign=rss",
      "date": "2026-03-13T12:37:17.000Z"
    },
    {
      "title": "Ex-Arsenal star to deny rape charges, court hears",
      "url": "https://www.bbc.com/news/articles/c4gqv9x3p40o?at_medium=RSS&at_campaign=rss",
      "date": "2026-03-13T11:48:37.000Z"
    }
  ]
}
