{
  "meta": {
    "key": "bbc",
    "label": "bbc",
    "source_url": "https://feeds.bbci.co.uk/news/rss.xml",
    "take": 2,
    "built_at": "2026-05-08T17:04:59.685Z"
  },
  "items": [
    {
      "title": "Ninth person arrested over Jewish ambulance arson",
      "url": "https://www.bbc.com/news/articles/c07281gye3mo?at_medium=RSS&at_campaign=rss",
      "date": "2026-05-08T16:42:22.000Z"
    },
    {
      "title": "Election results so far - and what's still to come",
      "url": "https://www.bbc.com/news/articles/cvgz155y9exo?at_medium=RSS&at_campaign=rss",
      "date": "2026-05-08T16:32:27.000Z"
    }
  ]
}
