{
  "meta": {
    "key": "bbc",
    "label": "bbc",
    "source_url": "https://feeds.bbci.co.uk/news/rss.xml",
    "take": 2,
    "built_at": "2026-05-11T16:25:35.780Z"
  },
  "items": [
    {
      "title": "Pupils hopeless and crying after 'poorly worded' Higher Maths exam",
      "url": "https://www.bbc.com/news/articles/cx21j20l9wlo?at_medium=RSS&at_campaign=rss",
      "date": "2026-05-11T16:13:30.000Z"
    },
    {
      "title": "'Total lack of respect': Macron interrupts speaker to ask for silence",
      "url": "https://www.bbc.com/news/videos/czx2wd20evyo?at_medium=RSS&at_campaign=rss",
      "date": "2026-05-11T16:10:18.000Z"
    }
  ]
}
