{
  "meta": {
    "key": "bbc",
    "label": "bbc",
    "source_url": "https://feeds.bbci.co.uk/news/rss.xml",
    "take": 2,
    "built_at": "2026-05-24T19:29:01.729Z"
  },
  "items": [
    {
      "title": "What happens now at relegated West Ham?",
      "url": "https://www.bbc.com/sport/football/articles/cvgz1zl14k3o?at_medium=RSS&at_campaign=rss",
      "date": "2026-05-24T19:19:40.000Z"
    },
    {
      "title": "Spurs survival celebrations can't disguise season of embarrassment",
      "url": "https://www.bbc.com/sport/football/articles/c5y7j7752ppo?at_medium=RSS&at_campaign=rss",
      "date": "2026-05-24T19:19:39.000Z"
    }
  ]
}
