{
  "meta": {
    "key": "bbc",
    "label": "bbc",
    "source_url": "https://feeds.bbci.co.uk/news/rss.xml",
    "take": 2,
    "built_at": "2026-03-26T06:07:53.330Z"
  },
  "items": [
    {
      "title": "NS&I set to pay millions in compensation to customers",
      "url": "https://www.bbc.com/news/articles/c3w3eg4n9zwo?at_medium=RSS&at_campaign=rss",
      "date": "2026-03-26T05:46:43.000Z"
    },
    {
      "title": "Australia's sunscreen regulator wants new rules after recent product scandal",
      "url": "https://www.bbc.com/news/articles/cql75nx0e0yo?at_medium=RSS&at_campaign=rss",
      "date": "2026-03-26T05:45:39.000Z"
    }
  ]
}
