{
  "meta": {
    "key": "bbc",
    "label": "bbc",
    "source_url": "https://feeds.bbci.co.uk/news/rss.xml",
    "take": 2,
    "built_at": "2026-05-10T17:42:54.784Z"
  },
  "items": [
    {
      "title": "Hull KR beat Wire to set up Wembley showdown with Wigan",
      "url": "https://www.bbc.com/sport/rugby-league/articles/c62xkr4kq50o?at_medium=RSS&at_campaign=rss",
      "date": "2026-05-10T17:37:21.000Z"
    },
    {
      "title": "Rayner issues 'last chance' warning to Starmer and backs Burnham to return",
      "url": "https://www.bbc.com/news/articles/c5yekp5j36zo?at_medium=RSS&at_campaign=rss",
      "date": "2026-05-10T17:24:33.000Z"
    }
  ]
}
