{
  "meta": {
    "key": "bbc",
    "label": "bbc",
    "source_url": "https://feeds.bbci.co.uk/news/rss.xml",
    "take": 2,
    "built_at": "2026-07-13T23:18:15.105Z"
  },
  "items": [
    {
      "title": "YouTube still recommending eating disorder videos to teens, research finds",
      "url": "https://www.bbc.co.uk/news/articles/c5yzn2g0xw9o?at_medium=RSS&at_campaign=rss",
      "date": "2026-07-13T23:05:00.000Z"
    },
    {
      "title": "No significant rain forecast for at least a week as UK heatwave continues",
      "url": "https://www.bbc.co.uk/weather/articles/cvge2zq0zg3o?at_medium=RSS&at_campaign=rss",
      "date": "2026-07-13T23:02:25.000Z"
    }
  ]
}
