{
  "meta": {
    "key": "bbc",
    "label": "bbc",
    "source_url": "https://feeds.bbci.co.uk/news/rss.xml",
    "take": 2,
    "built_at": "2026-03-05T06:41:25.027Z"
  },
  "items": [
    {
      "title": "The Papers: 'Trump's war goes global' and 'Labour ensnared by China spy probe'",
      "url": "https://www.bbc.com/news/articles/c1jkk9zjn25o?at_medium=RSS&at_campaign=rss",
      "date": "2026-03-05T06:36:35.000Z"
    },
    {
      "title": "How has Iran responded and which countries has it attacked?",
      "url": "https://www.bbc.com/news/articles/cx2dyz6p3weo?at_medium=RSS&at_campaign=rss",
      "date": "2026-03-05T06:10:55.000Z"
    }
  ]
}
