{
  "meta": {
    "key": "bbc",
    "label": "bbc",
    "source_url": "https://feeds.bbci.co.uk/news/rss.xml",
    "take": 2,
    "built_at": "2026-03-14T04:04:36.096Z"
  },
  "items": [
    {
      "title": "My stalker tricked random men into turning up at house for sex",
      "url": "https://www.bbc.com/news/articles/cev7lepl9jgo?at_medium=RSS&at_campaign=rss",
      "date": "2026-03-14T04:00:59.000Z"
    },
    {
      "title": "Maya Jama: 'My dream acting role is to play a monster or villain'",
      "url": "https://www.bbc.com/news/articles/cq57x0nlnv9o?at_medium=RSS&at_campaign=rss",
      "date": "2026-03-14T03:59:10.000Z"
    }
  ]
}
