{
  "meta": {
    "key": "bbc",
    "label": "bbc",
    "source_url": "https://feeds.bbci.co.uk/news/rss.xml",
    "take": 2,
    "built_at": "2026-03-27T20:30:16.979Z"
  },
  "items": [
    {
      "title": "Tiger Woods involved in Florida car crash",
      "url": "https://www.bbc.com/sport/golf/articles/cvg092kege7o?at_medium=RSS&at_campaign=rss",
      "date": "2026-03-27T20:20:57.000Z"
    },
    {
      "title": "Woods involved in Florida car crash",
      "url": "https://www.bbc.com/sport/golf/articles/cvg092kege7o?at_medium=RSS&at_campaign=rss",
      "date": "2026-03-27T20:20:57.000Z"
    }
  ]
}
