{
  "meta": {
    "key": "bbc",
    "label": "bbc",
    "source_url": "https://feeds.bbci.co.uk/news/rss.xml",
    "take": 2,
    "built_at": "2026-05-02T02:01:31.809Z"
  },
  "items": [
    {
      "title": "Boats, dancing and cake-cutting: Bermuda welcomes King Charles",
      "url": "https://www.bbc.com/news/articles/cvgz08k04jeo?at_medium=RSS&at_campaign=rss",
      "date": "2026-05-02T00:43:08.000Z"
    },
    {
      "title": "Trump tells Congress ceasefire means he does not need their approval for Iran war",
      "url": "https://www.bbc.com/news/articles/c4g4xexy4w7o?at_medium=RSS&at_campaign=rss",
      "date": "2026-05-02T00:41:43.000Z"
    }
  ]
}
