{
  "meta": {
    "key": "bbc",
    "label": "bbc",
    "source_url": "https://feeds.bbci.co.uk/news/rss.xml",
    "take": 2,
    "built_at": "2026-03-23T23:25:12.278Z"
  },
  "items": [
    {
      "title": "Arson attack on Jewish charity ambulances investigated by counter-terror police",
      "url": "https://www.bbc.com/news/articles/cwyj1p49gdpo?at_medium=RSS&at_campaign=rss",
      "date": "2026-03-23T22:26:55.000Z"
    },
    {
      "title": "Burnham should be allowed to stand as an MP, says Nandy",
      "url": "https://www.bbc.com/news/articles/cn89gjgl5yyo?at_medium=RSS&at_campaign=rss",
      "date": "2026-03-23T21:59:03.000Z"
    }
  ]
}
