{
  "meta": {
    "key": "bbc",
    "label": "bbc",
    "source_url": "https://feeds.bbci.co.uk/news/rss.xml",
    "take": 2,
    "built_at": "2026-04-10T08:17:55.264Z"
  },
  "items": [
    {
      "title": "Travellers told to allow more time for journeys as Irish fuel protests continue",
      "url": "https://www.bbc.com/news/articles/cy814wypp5go?at_medium=RSS&at_campaign=rss",
      "date": "2026-04-10T08:04:28.000Z"
    },
    {
      "title": "Melania Trump denies ties to Jeffrey Epstein and urges hearing for survivors",
      "url": "https://www.bbc.com/news/articles/c3ex07l1qvpo?at_medium=RSS&at_campaign=rss",
      "date": "2026-04-10T07:57:23.000Z"
    }
  ]
}
