{
  "meta": {
    "key": "bbc",
    "label": "bbc",
    "source_url": "https://feeds.bbci.co.uk/news/rss.xml",
    "take": 2,
    "built_at": "2026-04-12T01:52:38.401Z"
  },
  "items": [
    {
      "title": "Juddering McIlroy simply can't stop riding Masters rollercoaster",
      "url": "https://www.bbc.com/sport/golf/articles/czre4kdrk2do?at_medium=RSS&at_campaign=rss",
      "date": "2026-04-11T23:55:50.000Z"
    },
    {
      "title": "Hungarians decide whether to end 16 years of Orbán rule and elect rival",
      "url": "https://www.bbc.com/news/articles/cdxdepjrv95o?at_medium=RSS&at_campaign=rss",
      "date": "2026-04-11T23:25:42.000Z"
    }
  ]
}
