{
  "meta": {
    "key": "bbc",
    "label": "bbc",
    "source_url": "https://feeds.bbci.co.uk/news/rss.xml",
    "take": 2,
    "built_at": "2026-04-01T10:01:10.770Z"
  },
  "items": [
    {
      "title": "Man appears in court after pedestrians hit by car in Derby",
      "url": "https://www.bbc.com/news/articles/c4g8epx01gqo?at_medium=RSS&at_campaign=rss",
      "date": "2026-04-01T09:59:39.000Z"
    },
    {
      "title": "Dissident groups still have 'capacity and desire' to attack police, says NI justice minister",
      "url": "https://www.bbc.com/news/articles/cx2rxpegqn0o?at_medium=RSS&at_campaign=rss",
      "date": "2026-04-01T09:08:36.000Z"
    }
  ]
}
