{
  "meta": {
    "key": "bbc",
    "label": "bbc",
    "source_url": "https://feeds.bbci.co.uk/news/rss.xml",
    "take": 2,
    "built_at": "2026-03-08T17:17:02.202Z"
  },
  "items": [
    {
      "title": "Starmer and Trump speak for first time since president's Iran criticism",
      "url": "https://www.bbc.com/news/articles/c05v28eqjyvo?at_medium=RSS&at_campaign=rss",
      "date": "2026-03-08T16:56:34.000Z"
    },
    {
      "title": "'Mind boggles' at doubts over legality of Iran war, Israeli president says",
      "url": "https://www.bbc.com/news/articles/clyxp780xvro?at_medium=RSS&at_campaign=rss",
      "date": "2026-03-08T16:53:30.000Z"
    }
  ]
}
