{
  "meta": {
    "key": "bbc",
    "label": "bbc",
    "source_url": "https://feeds.bbci.co.uk/news/rss.xml",
    "take": 2,
    "built_at": "2026-03-11T10:31:33.834Z"
  },
  "items": [
    {
      "title": "Pro-Palestinian march banned after government approves Met request",
      "url": "https://www.bbc.com/news/articles/cm28gmlvedro?at_medium=RSS&at_campaign=rss",
      "date": "2026-03-11T09:59:26.000Z"
    },
    {
      "title": "Mortgage rates rise and deals pulled over Iran war turmoil",
      "url": "https://www.bbc.com/news/articles/c24dm9vgrz7o?at_medium=RSS&at_campaign=rss",
      "date": "2026-03-11T09:59:01.000Z"
    }
  ]
}
