{
  "meta": {
    "key": "bbc",
    "label": "bbc",
    "source_url": "https://feeds.bbci.co.uk/news/rss.xml",
    "take": 2,
    "built_at": "2026-02-17T04:12:17.492Z"
  },
  "items": [
    {
      "title": "Councils face 'uphill struggle' to be ready for local elections",
      "url": "https://www.bbc.com/news/articles/c043z5rzwg7o?at_medium=RSS&at_campaign=rss",
      "date": "2026-02-17T03:48:20.000Z"
    },
    {
      "title": "FBI won't co-operate on Alex Pretti investigation, state officials say",
      "url": "https://www.bbc.com/news/articles/crk8nxg1p4xo?at_medium=RSS&at_campaign=rss",
      "date": "2026-02-17T03:43:19.000Z"
    }
  ]
}
