{
  "meta": {
    "key": "bbc",
    "label": "bbc",
    "source_url": "https://feeds.bbci.co.uk/news/rss.xml",
    "take": 2,
    "built_at": "2026-03-21T10:19:03.828Z"
  },
  "items": [
    {
      "title": "UK allows US to use bases to strike Strait of Hormuz targets",
      "url": "https://www.bbc.com/news/articles/c36rny6xgppo?at_medium=RSS&at_campaign=rss",
      "date": "2026-03-21T10:13:02.000Z"
    },
    {
      "title": "BBC presenter Louise Minchin taken to hospital with frostbite during Artic challenge",
      "url": "https://www.bbc.com/news/articles/cddq40lypldo?at_medium=RSS&at_campaign=rss",
      "date": "2026-03-21T09:57:14.000Z"
    }
  ]
}
