{
  "meta": {
    "key": "bbc",
    "label": "bbc",
    "source_url": "https://feeds.bbci.co.uk/news/rss.xml",
    "take": 2,
    "built_at": "2026-06-06T19:30:07.270Z"
  },
  "items": [
    {
      "title": "Pope Leo begins Spain visit with praise for government",
      "url": "https://www.bbc.com/news/articles/c8d2pgjy4qgo?at_medium=RSS&at_campaign=rss",
      "date": "2026-06-06T18:34:26.000Z"
    },
    {
      "title": "Russell perplexed by struggles having arrived in Monaco playing mind games",
      "url": "https://www.bbc.com/sport/formula1/articles/cm2dn5gr253o?at_medium=RSS&at_campaign=rss",
      "date": "2026-06-06T18:27:45.000Z"
    }
  ]
}
