{
  "meta": {
    "key": "bbc",
    "label": "bbc",
    "source_url": "https://feeds.bbci.co.uk/news/rss.xml",
    "take": 2,
    "built_at": "2026-07-22T20:23:09.649Z"
  },
  "items": [
    {
      "title": "Menzies taken ill on stage at World Matchplay",
      "url": "https://www.bbc.co.uk/sport/darts/articles/cqjxv0v1dlpo?at_medium=RSS&at_campaign=rss",
      "date": "2026-07-22T20:09:59.000Z"
    },
    {
      "title": "Teenager drops social media addiction lawsuit against Meta",
      "url": "https://www.bbc.co.uk/news/articles/c5yrdg4q9vgo?at_medium=RSS&at_campaign=rss",
      "date": "2026-07-22T19:04:47.000Z"
    }
  ]
}
