{
  "meta": {
    "key": "bbc",
    "label": "bbc",
    "source_url": "https://feeds.bbci.co.uk/news/rss.xml",
    "take": 2,
    "built_at": "2026-03-07T21:14:29.754Z"
  },
  "items": [
    {
      "title": "UK to charter flight for British nationals out of Dubai",
      "url": "https://www.bbc.com/news/articles/c0432n5gl1zo?at_medium=RSS&at_campaign=rss",
      "date": "2026-03-07T21:04:54.000Z"
    },
    {
      "title": "'Fantastic French made to look ordinary as Scotland come of age'",
      "url": "https://www.bbc.com/sport/rugby-union/articles/cqj9pzxpg18o?at_medium=RSS&at_campaign=rss",
      "date": "2026-03-07T20:24:53.000Z"
    }
  ]
}
