{
  "meta": {
    "key": "bbc",
    "label": "bbc",
    "source_url": "https://feeds.bbci.co.uk/news/rss.xml",
    "take": 2,
    "built_at": "2026-03-09T12:42:21.400Z"
  },
  "items": [
    {
      "title": "Verstappen to compete in 'bucket list' 24-hour race",
      "url": "https://www.bbc.com/sport/motorsport/articles/cr5lj3lg857o?at_medium=RSS&at_campaign=rss",
      "date": "2026-03-09T12:25:16.000Z"
    },
    {
      "title": "Greg James to go ahead with Comic Relief challenge after dad suffers stroke",
      "url": "https://www.bbc.com/news/articles/c62d1w0qnq5o?at_medium=RSS&at_campaign=rss",
      "date": "2026-03-09T12:16:04.000Z"
    }
  ]
}
