{
  "meta": {
    "key": "bbc",
    "label": "bbc",
    "source_url": "https://feeds.bbci.co.uk/news/rss.xml",
    "take": 2,
    "built_at": "2026-04-15T21:44:16.510Z"
  },
  "items": [
    {
      "title": "Players told LIV Golf to run 'for many years' amid collapse rumours",
      "url": "https://www.bbc.com/sport/golf/articles/cx2dd2jr0mgo?at_medium=RSS&at_campaign=rss",
      "date": "2026-04-15T21:34:05.000Z"
    },
    {
      "title": "Social media leaders called to Downing Street over children's safety",
      "url": "https://www.bbc.com/news/articles/crl11ynjyn1o?at_medium=RSS&at_campaign=rss",
      "date": "2026-04-15T21:30:40.000Z"
    }
  ]
}
