{
  "meta": {
    "key": "crypto",
    "label": "decrypt",
    "source_url": "https://decrypt.co/feed",
    "take": 2,
    "built_at": "2026-05-21T17:40:28.673Z"
  },
  "items": [
    {
      "title": "Nvidia Beats, Stock Dumps—BofA Says Buy the Dip",
      "url": "https://decrypt.co/368650/bofa-nvidia-buy-top-pick-350-target",
      "date": "2026-05-21T17:39:17.000Z"
    },
    {
      "title": "US Government Makes $2 Billion Bet on Quantum Computing as Threat to Bitcoin Grows",
      "url": "https://decrypt.co/368647/us-government-2-billion-bet-quantum-computing-bitcoin-threat-grows",
      "date": "2026-05-21T17:24:00.000Z"
    }
  ]
}
