{
  "meta": {
    "key": "crypto",
    "label": "decrypt",
    "source_url": "https://decrypt.co/feed",
    "take": 2,
    "built_at": "2026-04-14T10:09:06.421Z"
  },
  "items": [
    {
      "title": "DOJ Opens $40M Compensation Process for OneCoin Crypto Fraud Victims",
      "url": "https://decrypt.co/364283/doj-opens-40m-compensation-process-for-onecoin-crypto-fraud-victims",
      "date": "2026-04-14T09:32:21.000Z"
    },
    {
      "title": "Crypto.com Reveals $1 Million in CRO Fighter Bonuses for White House UFC Fight",
      "url": "https://decrypt.co/364214/crypto-com-1-million-cro-fighter-bonuses-white-house-ufc-fight",
      "date": "2026-04-13T21:31:02.000Z"
    }
  ]
}
