{
  "meta": {
    "key": "crypto",
    "label": "decrypt",
    "source_url": "https://decrypt.co/feed",
    "take": 2,
    "built_at": "2026-04-18T11:28:51.640Z"
  },
  "items": [
    {
      "title": "Bitcoin Cracks 7-Month Ceiling. Can Bulls Push It Higher?",
      "url": "https://decrypt.co/364793/bitcoin-btc-price-breaks-seven-month-resistance",
      "date": "2026-04-17T21:11:36.000Z"
    },
    {
      "title": "You Can Now Use XRP on Solana—Here's How",
      "url": "https://decrypt.co/364792/you-can-now-use-xrp-solana-how",
      "date": "2026-04-17T20:40:39.000Z"
    }
  ]
}
