{
  "meta": {
    "key": "crypto",
    "label": "decrypt",
    "source_url": "https://decrypt.co/feed",
    "take": 2,
    "built_at": "2026-05-12T22:52:54.087Z"
  },
  "items": [
    {
      "title": "Hackers Insert Malware Into Mistral AI Software Download",
      "url": "https://decrypt.co/367683/hackers-insert-malware-mistral-ai",
      "date": "2026-05-12T22:26:18.000Z"
    },
    {
      "title": "JPMorgan Files to Launch Tokenized Money Market Fund on Ethereum",
      "url": "https://decrypt.co/367664/jpmorgan-tokenized-money-market-fund-ethereum",
      "date": "2026-05-12T21:31:14.000Z"
    }
  ]
}
