{
  "meta": {
    "key": "crypto",
    "label": "decrypt",
    "source_url": "https://decrypt.co/feed",
    "take": 2,
    "built_at": "2026-06-14T22:24:42.126Z"
  },
  "items": [
    {
      "title": "Reve 2.0 Review: The Best AI Image Generator for Layout Control",
      "url": "https://decrypt.co/371033/reve-2-review-best-ai-image-generator-layout-control",
      "date": "2026-06-14T19:11:33.000Z"
    },
    {
      "title": "Pokémon Card Sales Are Surging on Crypto Platforms—Just Don't Call It Gambling",
      "url": "https://decrypt.co/370978/pokemon-cards-surging-crypto-platforms-gambling",
      "date": "2026-06-14T13:01:03.000Z"
    }
  ]
}
