{
  "meta": {
    "key": "crypto",
    "label": "decrypt",
    "source_url": "https://decrypt.co/feed",
    "take": 2,
    "built_at": "2026-03-31T23:27:57.985Z"
  },
  "items": [
    {
      "title": "Crypto Startup Uses Polymarket to Bet on Its Own Fundraise, Blindsiding Backers",
      "url": "https://decrypt.co/362977/crypto-startup-polymarket-bet-fundraise-blindsiding-backers",
      "date": "2026-03-31T21:07:24.000Z"
    },
    {
      "title": "If You Hold Solana on Magic Eden's Wallet, It's Time to Move It or Lose It",
      "url": "https://decrypt.co/362979/if-you-hold-solana-magic-eden-wallet-time-to-move",
      "date": "2026-03-31T21:06:15.000Z"
    }
  ]
}
