{
  "meta": {
    "key": "crypto",
    "label": "decrypt",
    "source_url": "https://decrypt.co/feed",
    "take": 2,
    "built_at": "2026-04-06T14:07:09.696Z"
  },
  "items": [
    {
      "title": "Strategy Resumes Bitcoin Treasury Buys With $330M Purchase",
      "url": "https://decrypt.co/363373/strategy-resumes-bitcoin-treasury-buys-with-330m-purchase",
      "date": "2026-04-06T12:43:05.000Z"
    },
    {
      "title": "Morning Minute: North Korea Hacks Drift for $285M",
      "url": "https://decrypt.co/363370/morning-minute-north-korea-hacks-drift-for-285m",
      "date": "2026-04-06T12:18:33.000Z"
    }
  ]
}
