{
  "meta": {
    "key": "crypto",
    "label": "decrypt",
    "source_url": "https://decrypt.co/feed",
    "take": 2,
    "built_at": "2026-06-15T13:02:39.374Z"
  },
  "items": [
    {
      "title": "Philippines Issues Stricter Crypto Listing Rules, Bans Privacy Coins",
      "url": "https://decrypt.co/371124/philippines-issues-stricter-crypto-listing-rules-bans-privacy-coins",
      "date": "2026-06-15T11:27:19.000Z"
    },
    {
      "title": "Bitcoin Tops $65K on US-Iran Deal, But Traders Remain Skeptical",
      "url": "https://decrypt.co/371121/bitcoin-tops-65k-on-us-iran-deal-but-traders-remain-skeptical",
      "date": "2026-06-15T11:03:14.000Z"
    }
  ]
}
