{"updated":"2026-06-02T21:08:49.545Z","items":[{"title":"Strategy Shares Fall for Second Straight Day After $56 Billion Bitcoin Giant Sells BTC","url":"https://decrypt.co/369788/strategy-shares-fall-second-straight-day-bitcoin-giant-sells-btc","source":"decrypt","stamp":"LIVE"},{"title":"Microsoft Turns OpenClaw Into an Enterprise AI Agent With Scout","url":"https://decrypt.co/369781/microsoft-scout-openclaw-enterprise-ai-agent","source":"decrypt","stamp":"LIVE"},{"title":"Bernie Sanders, Elizabeth Warren Urge Labor Department to Drop Bitcoin, Crypto 401K Plan","url":"https://decrypt.co/369773/bernie-sanders-elizabeth-warren-labor-dept-drop-bitcoin-crypto-401k-plan","source":"decrypt","stamp":"LIVE"},{"title":"Where Does Bitcoin Go From Here? This Is What the Charts Say","url":"https://decrypt.co/369750/bitcoin-price-next-charts-technical-analysis","source":"decrypt","stamp":"LIVE"},{"title":"New York’s Crypto Watchdog Teams With EU to Police Stablecoins","url":"https://decrypt.co/369749/new-yorks-crypto-watchdog-teams-eu-police-stablecoins","source":"decrypt","stamp":"LIVE"}]}
