{
  "meta": {
    "key": "hn",
    "label": "hn",
    "source_url": "https://hnrss.org/newest?points=1",
    "take": 2,
    "built_at": "2026-02-22T04:09:56.668Z"
  },
  "items": [
    {
      "title": "Ways to Harness AI",
      "url": "https://lukasfischer.ch/node/37",
      "date": "2026-02-22T04:06:48.000Z"
    },
    {
      "title": "Mac Media Stack – One-command Plex server with auto-healing on macOS",
      "url": "https://github.com/liamvibecodes/mac-media-stack",
      "date": "2026-02-22T04:06:43.000Z"
    }
  ]
}
