{
  "meta": {
    "key": "hn",
    "label": "hn",
    "source_url": "https://hnrss.org/newest?points=1",
    "take": 2,
    "built_at": "2026-03-24T23:24:59.433Z"
  },
  "items": [
    {
      "title": "Does nobody care about not being able to copy from Slack anymore?",
      "url": "https://news.ycombinator.com/item?id=47510993",
      "date": "2026-03-24T23:21:12.000Z"
    },
    {
      "title": "A daily brief of what the top podcasts are saying",
      "url": "https://www.podsnacks.com/",
      "date": "2026-03-24T23:19:43.000Z"
    }
  ]
}
