{
  "meta": {
    "key": "hn",
    "label": "hn",
    "source_url": "https://hnrss.org/newest?points=1",
    "take": 2,
    "built_at": "2026-02-19T16:42:35.900Z"
  },
  "items": [
    {
      "title": "The Musidex: A physical music library for the streaming era",
      "url": "https://hannahilea.com/blog/musidex/",
      "date": "2026-02-19T16:42:04.000Z"
    },
    {
      "title": "I'm Glad the Internet Wasn't Watching My Worst Breakup",
      "url": "https://yinsuboaster.substack.com/p/im-glad-the-internet-wasnt-watching",
      "date": "2026-02-19T16:42:01.000Z"
    }
  ]
}
