{
  "meta": {
    "key": "hn",
    "label": "hn",
    "source_url": "https://hnrss.org/newest?points=1",
    "take": 2,
    "built_at": "2026-05-09T10:50:26.028Z"
  },
  "items": [
    {
      "title": "Kanvly – notes and boards with AI, now on iOS",
      "url": "https://kanvly.com",
      "date": "2026-05-09T10:39:45.000Z"
    },
    {
      "title": "Lua as a practical \"soft-bedrock\" language",
      "url": "https://portal.mozz.us/gemini/zaibatsu.circumlunar.space/~solderpunk/gemlog/lua-as-a-practical-soft-bedrock-language.gmi",
      "date": "2026-05-09T10:35:18.000Z"
    }
  ]
}
