{
  "meta": {
    "key": "hn",
    "label": "hn",
    "source_url": "https://hnrss.org/newest?points=1",
    "take": 2,
    "built_at": "2026-03-03T20:25:21.431Z"
  },
  "items": [
    {
      "title": "Dependency Management Is CI/CD Missing Primitive",
      "url": "https://infraweekly.substack.com/p/issue-117",
      "date": "2026-03-03T20:19:11.000Z"
    },
    {
      "title": "Public Grok is toxic and unable to reason properly. This affects discourse",
      "url": "https://twitter.com/GregMozart/status/2028927951345992176",
      "date": "2026-03-03T20:19:10.000Z"
    }
  ]
}
