{
  "meta": {
    "key": "hn",
    "label": "hn",
    "source_url": "https://hnrss.org/newest?points=1",
    "take": 2,
    "built_at": "2026-02-23T17:56:34.765Z"
  },
  "items": [
    {
      "title": "Show HN: OmniGlass – An open-source, sandboxed Visual Action Engine",
      "url": "https://github.com/goshtasb/OmniGlass",
      "date": "2026-02-23T17:53:09.000Z"
    },
    {
      "title": "25 Years of Eggs",
      "url": "https://www.john-rush.com/posts/eggs-25-years-20260219.html",
      "date": "2026-02-23T17:53:02.000Z"
    }
  ]
}
