{
  "meta": {
    "key": "hn",
    "label": "hn",
    "source_url": "https://hnrss.org/newest?points=1",
    "take": 2,
    "built_at": "2026-07-20T16:29:17.918Z"
  },
  "items": [
    {
      "title": "A Power Trip",
      "url": "https://hackerfactor.com/blog/index.php?/archives/1099-On-a-Power-Trip.html",
      "date": "2026-07-20T16:26:45.000Z"
    },
    {
      "title": "There have only been 5 ethical NBA champions in the last 25 years",
      "url": "https://pudding.cool/2026/06/ethical-champions/",
      "date": "2026-07-20T16:25:21.000Z"
    }
  ]
}
