{
  "meta": {
    "key": "hn",
    "label": "hn",
    "source_url": "https://hnrss.org/newest?points=1",
    "take": 2,
    "built_at": "2026-06-03T00:44:07.022Z"
  },
  "items": [
    {
      "title": "Peach – a free zero-knowledge password manager with paper disaster recovery",
      "url": "https://peachpasswords.com/",
      "date": "2026-06-03T00:40:57.000Z"
    },
    {
      "title": "New Zealand testing of Elon Musk's Starshield 'significant', US expert says",
      "url": "https://www.rnz.co.nz/news/science-and-technology/597104/new-zealand-testing-of-elon-musk-s-starshield-significant-us-expert-says",
      "date": "2026-06-03T00:36:30.000Z"
    }
  ]
}
