{
  "meta": {
    "key": "hn",
    "label": "hn",
    "source_url": "https://hnrss.org/newest?points=1",
    "take": 2,
    "built_at": "2026-05-05T11:54:45.245Z"
  },
  "items": [
    {
      "title": "Topaz vs. Azurite: what works locally and what doesn't",
      "url": "https://topaz.thecloudtheory.com/blog/topaz-vs-azurite/",
      "date": "2026-05-05T11:54:26.000Z"
    },
    {
      "title": "Why ADHD Is the Cheat Code of the AI Era",
      "url": "https://www.airsugar.com/p/why-adhd-is-the-cheat-code-of-the",
      "date": "2026-05-05T11:52:48.000Z"
    }
  ]
}
