{
  "meta": {
    "key": "hn",
    "label": "hn",
    "source_url": "https://hnrss.org/newest?points=1",
    "take": 2,
    "built_at": "2026-05-28T22:31:50.160Z"
  },
  "items": [
    {
      "title": "Protecting communities from scrapers and platform abuse: modnews",
      "url": "https://old.reddit.com/r/modnews/comments/1tq9vxo/protecting_communities_from_scrapers_and_platform/",
      "date": "2026-05-28T22:12:39.000Z"
    },
    {
      "title": "Cyber Offense: How Far Can Private Organizations Go?",
      "url": "https://www.lawfaremedia.org/article/cyber-offense--how-far-can-private-organizations-go",
      "date": "2026-05-28T22:12:08.000Z"
    }
  ]
}
