{
  "meta": {
    "key": "hn",
    "label": "hn",
    "source_url": "https://hnrss.org/newest?points=1",
    "take": 2,
    "built_at": "2026-04-04T13:47:22.027Z"
  },
  "items": [
    {
      "title": "The ICEBlock App Has Helped People Avoid Immigration Agents. Is It Legal?",
      "url": "https://www.newyorker.com/news/the-lede/the-rise-and-fall-of-ice-tracking-apps",
      "date": "2026-04-04T13:45:52.000Z"
    },
    {
      "title": "An AI agent called every pub in Ireland to index the cost of a Guinness",
      "url": "https://guinndex.ai",
      "date": "2026-04-04T13:45:24.000Z"
    }
  ]
}
