{
  "meta": {
    "key": "hn",
    "label": "hn",
    "source_url": "https://hnrss.org/newest?points=1",
    "take": 2,
    "built_at": "2026-02-18T14:03:11.775Z"
  },
  "items": [
    {
      "title": "A Philologist on Esperanto",
      "url": "https://tolkiengateway.net/wiki/A_Philologist_on_Esperanto",
      "date": "2026-02-18T14:02:30.000Z"
    },
    {
      "title": "Baseline Core – Open-source skill system that wires your business to AI",
      "url": "https://github.com/TrentM6/baseline-core",
      "date": "2026-02-18T14:01:51.000Z"
    }
  ]
}
