{
  "meta": {
    "key": "hn",
    "label": "hn",
    "source_url": "https://hnrss.org/newest?points=1",
    "take": 2,
    "built_at": "2026-05-05T07:57:19.894Z"
  },
  "items": [
    {
      "title": "HeadVis: An Interactive Tool for Investigating Attention Heads",
      "url": "https://transformer-circuits.pub/2026/headvis/index.html",
      "date": "2026-05-05T07:54:07.000Z"
    },
    {
      "title": "All left of center parties in Germany are advising their members to leave X",
      "url": "https://table.media/berlin/news/wirverlassenx-gruene-spd-und-linke-empfehlen-ihren-mitgliedern-den-ausstieg-aus-dem-sozialen-netzwerk",
      "date": "2026-05-05T07:49:31.000Z"
    }
  ]
}
