{
  "meta": {
    "key": "hn",
    "label": "hn",
    "source_url": "https://hnrss.org/newest?points=1",
    "take": 2,
    "built_at": "2026-05-26T16:16:56.209Z"
  },
  "items": [
    {
      "title": "What Happened to the Locusts?",
      "url": "https://explosion-scratch.github.io/locusts/",
      "date": "2026-05-26T16:15:17.000Z"
    },
    {
      "title": "Show HN: What story are you telling? (narrative archetypes tool)",
      "url": "https://arc.quanten.co/tools/logline",
      "date": "2026-05-26T16:15:07.000Z"
    }
  ]
}
