{
  "updated_iso": "2026-05-26T18:58:25.046Z",
  "updated_local": "5/26/2026, 6:58:25 PM",
  "sections": {
    "crypto": [
      {
        "title": "TeraWulf Stock Pops as Bitcoin Miner Acquires Kentucky Site to Meet AI Power Demands",
        "url": "https://decrypt.co/369053/terawulf-bitcoin-miner-kentucky-site-ai-power-demands",
        "source": "crypto",
        "time": "Tue, 26 May 2026 18:23:18 +0000"
      },
      {
        "title": "Inaudible Audio Attacks Can Hijack AI Voice Models, Study Finds",
        "url": "https://decrypt.co/369042/inaudible-audio-attacks-hijack-ai-voice-models",
        "source": "crypto",
        "time": "Tue, 26 May 2026 18:17:04 +0000"
      },
      {
        "title": "UK Issues Sanctions Against Justin Sun&#39;s HTX, Other Crypto Firms Over Alleged Russia Ties",
        "url": "https://decrypt.co/369047/uk-issues-sanctions-against-justin-sun-htx-crypto-firms-russia-ties",
        "source": "crypto",
        "time": "Tue, 26 May 2026 18:15:34 +0000"
      },
      {
        "title": "Tom Lee&#39;s BitMine Makes Biggest Ethereum Buy Yet in 2026",
        "url": "https://decrypt.co/369011/tom-lee-bitmine-makes-biggest-ethereum-buy-2026",
        "source": "crypto",
        "time": "Tue, 26 May 2026 15:56:26 +0000"
      },
      {
        "title": "Indonesia Blocks Polymarket After Bets on President’s Early Departure",
        "url": "https://decrypt.co/369020/indonesia-blocks-polymarket-after-bets-on-presidents-early-departure",
        "source": "crypto",
        "time": "Tue, 26 May 2026 15:33:37 +0000"
      }
    ],
    "hacker": [
      {
        "title": "The Ballad of TIGIT",
        "url": "https://www.owlposting.com/p/the-ballad-of-tigit",
        "source": "hn",
        "time": "5/26/2026, 3:47:32 PM"
      },
      {
        "title": "Launch HN: Minicor (YC P26) – Windows desktop automations at scale",
        "url": "https://www.minicor.com/",
        "source": "hn",
        "time": "5/26/2026, 2:57:27 PM"
      },
      {
        "title": "A few interesting modern pixel fonts",
        "url": "https://unsung.aresluna.org/a-few-interesting-modern-pixel-fonts/",
        "source": "hn",
        "time": "5/25/2026, 8:41:49 PM"
      },
      {
        "title": "Spain blocks prediction markets Polymarket, Kalshi over lack of gambling licence",
        "url": "https://www.reuters.com/business/spain-blocks-prediction-markets-polymarket-kalshi-over-lack-gambling-licences-2026-05-26/",
        "source": "hn",
        "time": "5/26/2026, 1:08:13 PM"
      },
      {
        "title": "Stack Overflow’s forum is dead but the company’s still kicking",
        "url": "https://wiert.me/2026/05/26/stack-overflows-forum-is-dead-thanks-to-ai-but-the-companys-still-kicking-thanks-to-ai-sherwood-news/",
        "source": "hn",
        "time": "5/26/2026, 5:17:12 PM"
      }
    ],
    "world": [
      {
        "title": "UK's hottest May day record broken for second day in a row",
        "url": "https://www.bbc.com/news/articles/clypp7ljvpvo?at_medium=RSS&amp;at_campaign=rss",
        "source": "world",
        "time": "Tue, 26 May 2026 18:38:03 GMT"
      },
      {
        "title": "Iran condemns US strikes as 'gross violation' of ceasefire",
        "url": "https://www.bbc.com/news/articles/c4g44yl7q70o?at_medium=RSS&amp;at_campaign=rss",
        "source": "world",
        "time": "Tue, 26 May 2026 15:15:29 GMT"
      },
      {
        "title": "Sentences of boys spared custody over rape referred to Court of Appeal",
        "url": "https://www.bbc.com/news/articles/c5y779yeq0eo?at_medium=RSS&amp;at_campaign=rss",
        "source": "world",
        "time": "Tue, 26 May 2026 13:03:36 GMT"
      },
      {
        "title": "Almost 1,000 migrants cross Channel over bank holiday",
        "url": "https://www.bbc.com/news/articles/cy422k3z83vo?at_medium=RSS&amp;at_campaign=rss",
        "source": "world",
        "time": "Tue, 26 May 2026 16:39:41 GMT"
      },
      {
        "title": "'Bullying' and 'overbearing' behaviour behind abrupt BP chairman removal",
        "url": "https://www.bbc.com/news/articles/cjrppppwvwlo?at_medium=RSS&amp;at_campaign=rss",
        "source": "world",
        "time": "Tue, 26 May 2026 15:04:39 GMT"
      }
    ],
    "projects": [
      {
        "title": "Browse Arduino Projects on Hackster",
        "url": "https://www.hackster.io/arduino/projects",
        "source": "hackster",
        "time": ""
      },
      {
        "title": "Explore Hackster News",
        "url": "https://www.hackster.io/news",
        "source": "hackster",
        "time": ""
      },
      {
        "title": "View All Projects",
        "url": "https://www.hackster.io/projects",
        "source": "hackster",
        "time": ""
      }
    ]
  }
}
