{
  "meta": {
    "key": "ufo",
    "label": "ufo / uap",
    "source_url": "https://news.google.com/rss/search?q=(ufo%20OR%20uap%20OR%20unidentified%20aerial%20phenomena)%20when%3A7d&hl=en-US&gl=US&ceid=US%3Aen",
    "take": 1,
    "built_at": "2026-04-17T21:35:06.521Z"
  },
  "items": [
    {
      "title": "The Pentagon Missed A Major Deadline To Release UFO Footage - Here's What We Know - bgr.com",
      "url": "https://news.google.com/rss/articles/CBMifkFVX3lxTE16R2dBa1ZJaTl0RkI4cnd5MUpjdVN5Sm5sXzQwRVpGSW83bFN4bkl0Ym9Pd2FrdlhPbnUtRlRMQzVoR01PQWsyTzh2QXNEd3VTcHhXU2M2RzVYSUxzNHRtTkRRTDl6X2xHUTN0R0pUNmNYTlBRNVFCOWRtOU9HQQ?oc=5",
      "date": "2026-04-17T21:17:00.000Z"
    }
  ]
}
