{
  "meta": {
    "key": "ufo",
    "label": "ufo / uap",
    "source_url": "https://news.google.com/rss/search?q=(ufo%20OR%20uap%20OR%20unidentified%20aerial%20phenomena)%20when%3A7d&hl=en-US&gl=US&ceid=US%3Aen",
    "take": 1,
    "built_at": "2026-02-27T20:20:53.005Z"
  },
  "items": [
    {
      "title": "President George HW Bush ‘knew’ of 1964 alien contact with humans in New Mexico: documentary - AOL.com",
      "url": "https://news.google.com/rss/articles/CBMifkFVX3lxTE13ZkVIbC1ibUhkQi04YTh4RUtxakRBMWNIRmYxY1hYbWN2aXdCN3otNWNVWjdiODBDTk90Nm5QbjNNRzJxRGZCM0E4MHRJc0s2VXFraFpPWkdiTEliTk9EQ1pfYjdRaFgzcUVMTHplNlZSUXRlemVFaVZDZUlIZw?oc=5",
      "date": "2026-02-27T16:46:20.000Z"
    }
  ]
}
